migi/__init__.py
migi/__main__.py
migi/_internal.py
migi/console.py
migi/decorators.py
migi/exceptions.py
migi/manifest.py
migi/module.py
migi/platform.py
migi/session.py
migi/utils.py
migi/bin/_migi.cp3-win32.pyd
migi/bin/_migi.cp3-win_amd64.pyd
migi/bin/migi.cp3-win32.dll
migi/bin/migi.cp3-win_amd64.dll
migi/structs/__init__.py
migi/structs/inet.py
migi/structs/stl.py
migi-0.0.19.dist-info/LICENSE
migi-0.0.19.dist-info/METADATA
migi-0.0.19.dist-info/WHEEL
migi-0.0.19.dist-info/top_level.txt
migi-0.0.19.dist-info/RECORD
