Metadata-Version: 2.1
Name: migi
Version: 0.0.19
Summary: A powerful and versatile dynamic instrumentation toolkit
Home-page: https://github.com/nomadsinteractive/migi
Author: Vintage Mars
Author-email: nomadsinteractive@gmail.com
License: UNKNOWN
Project-URL: Bug Tracker, https://github.com/nomadsinteractive/migi/issues
Platform: UNKNOWN
Classifier: Development Status :: 3 - Alpha
Classifier: Intended Audience :: Developers
Classifier: Intended Audience :: Science/Research
Classifier: Intended Audience :: System Administrators
Classifier: Programming Language :: C++
Classifier: Programming Language :: Python :: 3
Classifier: Programming Language :: Python :: 3.7
Classifier: Programming Language :: Python :: 3.8
Classifier: Programming Language :: Python :: 3.9
Classifier: Programming Language :: Python :: 3.10
Classifier: License :: OSI Approved :: Apache Software License
Classifier: Operating System :: Microsoft :: Windows
Requires-Python: >=3.7
License-File: LICENSE
